extracts/__init__.py
extracts/_fetchers.py
extracts/_version.py
extracts/data/registry.txt
extracts/data/barrett2020/table1.tsv
extracts/data/barrett2020/table2.tsv
extracts-0.0.1.dev2.dist-info/METADATA
extracts-0.0.1.dev2.dist-info/WHEEL
extracts-0.0.1.dev2.dist-info/top_level.txt
extracts-0.0.1.dev2.dist-info/RECORD
