Metadata-Version: 2.1
Name: extracts
Version: 0.0.1.dev2
Summary: Load tables, figures, and text manually extracted from published journal articles.
Author-email: Remington Mallett <mallett.remy@gmail.com>
Maintainer-email: Remington Mallett <mallett.remy@gmail.com>
Project-URL: Homepage, https://github.com/remrama/extracts
Keywords: data,meta-analysis
Classifier: Development Status :: 1 - Planning
Classifier: License :: OSI Approved :: BSD License
Classifier: Operating System :: OS Independent
Classifier: Intended Audience :: Science/Research
Classifier: Topic :: Scientific/Engineering
Classifier: Programming Language :: Python
Classifier: Programming Language :: Python :: 3
Classifier: Programming Language :: Python :: 3.7
Classifier: Programming Language :: Python :: 3.8
Classifier: Programming Language :: Python :: 3.9
Classifier: Programming Language :: Python :: 3.10
Classifier: Programming Language :: Python :: 3.11
Classifier: Programming Language :: Python :: 3.12
Classifier: Programming Language :: Python :: 3.13
Requires-Python: >=3.8
Requires-Dist: pandas >=2.0
Requires-Dist: pooch >=1.8
Provides-Extra: dev
Requires-Dist: tabula-py >=2.9 ; extra == 'dev'
